eeprom/__init__.py
eeprom/cbor_eeprom.py
eeprom/device_types.py
eeprom/eeprom.py
eeprom/util.py
eeprom-0.1.0.dist-info/LICENSE
eeprom-0.1.0.dist-info/METADATA
eeprom-0.1.0.dist-info/WHEEL
eeprom-0.1.0.dist-info/entry_points.txt
eeprom-0.1.0.dist-info/top_level.txt
eeprom-0.1.0.dist-info/RECORD
